chatpywork/__init__.py
chatpywork/room.py
chatpywork-1.3.0.dist-info/LICENSE
chatpywork-1.3.0.dist-info/METADATA
chatpywork-1.3.0.dist-info/WHEEL
chatpywork-1.3.0.dist-info/top_level.txt
chatpywork-1.3.0.dist-info/RECORD
