Metadata-Version: 2.1
Name: chatpywork
Version: 1.3.0
Summary: python wrapper for ChatWork API v2
Home-page: https://github.com/tannakaken/chatpywork
Author: tannakaken
Author-email: tannakaken@gmail.com
Maintainer: tannakaken
Maintainer-email: tannakaken@gmail.com
License: MIT
Keywords: chatwork
Platform: UNKNOWN
Classifier: License :: OSI Approved :: MIT License
Classifier: Programming Language :: Python :: 3.7
Requires-Dist: requests
